PyWrikeAssist/__init__.py
PyWrikeAssist/create_delete_folders.py
PyWrikeAssist/create_update_delete_tasks.py
PyWrikeAssist/new_space.py
PyWrikeAssist/propagate_tasks.py
PyWrikeAssist/wrike_export.py
PyWrikeAssist/wrike_export_json.py
PyWrikeAssist-0.72.dist-info/METADATA
PyWrikeAssist-0.72.dist-info/WHEEL
PyWrikeAssist-0.72.dist-info/top_level.txt
PyWrikeAssist-0.72.dist-info/RECORD
